ocf_blosc2/__init__.py
ocf_blosc2/ocf_blosc2.py
ocf_blosc2/ocf_blosc2_v3.py
ocf_blosc2-0.0.14.dist-info/LICENSE
ocf_blosc2-0.0.14.dist-info/METADATA
ocf_blosc2-0.0.14.dist-info/WHEEL
ocf_blosc2-0.0.14.dist-info/entry_points.txt
ocf_blosc2-0.0.14.dist-info/top_level.txt
ocf_blosc2-0.0.14.dist-info/RECORD
