Metadata-Version: 2.2
Name: ocf_blosc2
Version: 0.0.14
Summary: OCF Blosc2 is a codec for numcodecs for compressing image data in Zarr/Xarray
Author: Jacob Bieker
Author-email: info@openclimatefix.org
License: MIT
License-File: LICENSE
Requires-Dist: numpy
Requires-Dist: blosc2
Requires-Dist: numcodecs
Requires-Dist: zarr>3
Dynamic: author
Dynamic: author-email
Dynamic: description
Dynamic: description-content-type
Dynamic: license
Dynamic: requires-dist
Dynamic: summary
